drosSRA/__init__.py
drosSRA/drosSRA.py
drosSRA/rnaseq_metadata.tsv
drosSRA-0.4.5.dist-info/AUTHORS.rst
drosSRA-0.4.5.dist-info/LICENSE
drosSRA-0.4.5.dist-info/METADATA
drosSRA-0.4.5.dist-info/WHEEL
drosSRA-0.4.5.dist-info/entry_points.txt
drosSRA-0.4.5.dist-info/top_level.txt
drosSRA-0.4.5.dist-info/RECORD
