Metadata-Version: 2.1
Name: drosSRA
Version: 0.4.5
Summary: drosSRA builds a url for visualization of tracks based on user specified parameters (i.e. sex, tissue, cell type)
Home-page: https://github.com/isabelleberger/drosSRA
Author: Isabelle Berger
Author-email: isabelle@gwu.edu
License: MIT license
Keywords: drosSRA
Platform: UNKNOWN
Classifier: Development Status :: 2 - Pre-Alpha
Classifier: Intended Audience :: Developers
Classifier: License :: OSI Approved :: MIT License
Classifier: Natural Language :: English
Classifier: Programming Language :: Python :: 2
Classifier: Programming Language :: Python :: 2.7
Classifier: Programming Language :: Python :: 3
Classifier: Programming Language :: Python :: 3.4
Classifier: Programming Language :: Python :: 3.5
Classifier: Programming Language :: Python :: 3.6
Classifier: Programming Language :: Python :: 3.7
Requires-Dist: pandas
Requires-Dist: argparse
